error_catcher/__init__.py
error_catcher/error_catcher.py
error_catcher-0.4.dist-info/LICENSE
error_catcher-0.4.dist-info/METADATA
error_catcher-0.4.dist-info/WHEEL
error_catcher-0.4.dist-info/top_level.txt
error_catcher-0.4.dist-info/RECORD
