Metadata-Version: 2.1
Name: error-catcher
Version: 0.4
Summary: A decorator to trace error and catch variables.
Home-page: https://github.com/wenzhi-ding/error_catcher
Author: Wenzhi Ding
Author-email: wenzhi.ding@foxmail.com
License: UNKNOWN
Platform: UNKNOWN
Classifier: Programming Language :: Python :: 3
Classifier: License :: OSI Approved :: MIT License
Classifier: Operating System :: OS Independent
Requires-Python: >=3.6
